LICENSE
MANIFEST.in
setup.py
synq/__init__.py
synq.egg-info/PKG-INFO
synq.egg-info/SOURCES.txt
synq.egg-info/dependency_links.txt
synq.egg-info/requires.txt
synq.egg-info/top_level.txt
tests/__init__.py
tests/video/__init__.py
tests/video/create.py
tests/video/details.py
tests/video/query.py
tests/video/query_simple.py
tests/video/update.py
tests/video/upload-and-deliver-bad-content-type.py
tests/video/upload-and-deliver-bad-key.py
tests/video/upload-and-deliver.py
tests/video/upload.py
tests/video/uploader.py