Metadata-Version: 1.0
Name: synq
Version: 1.0.0
Summary: SYNQ Video API
Home-page: https://synq.fm
Author: synq
Author-email: sales@synq.fm
License: MIT
Keywords: SYNQ Video API
Platform: UNKNOWN
